{"LawSearch": {
    "law": [
        {
            "현행연혁코드": "연혁",
            "법령일련번호": "267399",
            "자법타법여부": "",
            "법령상세링크": "/DRF/lawService.do?OC=knowhow1&target=eflaw&MST=267399&type=HTML&mobileYn=&efYd=20250621",
            "법령명한글": "제주특별자치도 설치 및 국제자유도시 조성을 위한 특별법",
            "법령구분명": "법률",
            "소관부처명": "국토교통부,행정안전부",
            "공포번호": "20593",
            "제개정구분명": "타법개정",
            "소관부처코드": "1613000,1741000",
            "id": "801",
            "법령ID": "010162",
            "공동부령정보": "",
            "시행일자": "20250621",
            "공포일자": "20241220",
            "법령약칭명": "제주특별법"
        },
        {
            "현행연혁코드": "연혁",
            "법령일련번호": "265477",
            "자법타법여부": "",
            "법령상세링크": "/DRF/lawService.do?OC=knowhow1&target=eflaw&MST=265477&type=HTML&mobileYn=&efYd=20250621",
            "법령명한글": "제주특별자치도 설치 및 국제자유도시 조성을 위한 특별법",
            "법령구분명": "법률",
            "소관부처명": "국토교통부,행정안전부",
            "공포번호": "20445",
            "제개정구분명": "타법개정",
            "소관부처코드": "1613000,1741000",
            "id": "802",
            "법령ID": "010162",
            "공동부령정보": "",
            "시행일자": "20250621",
            "공포일자": "20240920",
            "법령약칭명": "제주특별법"
        },
        {
            "현행연혁코드": "현행",
            "법령일련번호": "272521",
            "자법타법여부": "",
            "법령상세링크": "/DRF/lawService.do?OC=knowhow1&target=eflaw&MST=272521&type=HTML&mobileYn=&efYd=20250621",
            "법령명한글": "정신건강증진 및 정신질환자 복지서비스 지원에 관한 법률 시행령",
            "법령구분명": "대통령령",
            "소관부처명": "보건복지부",
            "공포번호": "35597",
            "제개정구분명": "타법개정",
            "소관부처코드": "1352000",
            "id": "803",
            "법령ID": "004830",
            "공동부령정보": "",
            "시행일자": "20250621",
            "공포일자": "20250620",
            "법령약칭명": "정신건강복지법 시행령"
        },
        {
            "현행연혁코드": "현행",
            "법령일련번호": "272551",
            "자법타법여부": "",
            "법령상세링크": "/DRF/lawService.do?OC=knowhow1&target=eflaw&MST=272551&type=HTML&mobileYn=&efYd=20250621",
            "법령명한글": "전문간호사 자격인정 등에 관한 규칙",
            "법령구분명": "보건복지부령",
            "소관부처명": "보건복지부",
            "공포번호": "01118",
            "제개정구분명": "타법개정",
            "소관부처코드": "1352000",
            "id": "804",
            "법령ID": "010250",
            "공동부령정보": "",
            "시행일자": "20250621",
            "공포일자": "20250620",
            "법령약칭명": ""
        },
        {
            "현행연혁코드": "현행",
            "법령일련번호": "272519",
            "자법타법여부": "",
            "법령상세링크": "/DRF/lawService.do?OC=knowhow1&target=eflaw&MST=272519&type=HTML&mobileYn=&efYd=20250621",
            "법령명한글": "장애인활동 지원에 관한 법률 시행령",
            "법령구분명": "대통령령",
            "소관부처명": "보건복지부",
            "공포번호": "35597",
            "제개정구분명": "타법개정",
            "소관부처코드": "1352000",
            "id": "805",
            "법령ID": "011439",
            "공동부령정보": "",
            "시행일자": "20250621",
            "공포일자": "20250620",
            "법령약칭명": "장애인활동법 시행령"
        },
        {
            "현행연혁코드": "연혁",
            "법령일련번호": "265475",
            "자법타법여부": "",
            "법령상세링크": "/DRF/lawService.do?OC=knowhow1&target=eflaw&MST=265475&type=HTML&mobileYn=&efYd=20250621",
            "법령명한글": "장애인복지법",
            "법령구분명": "법률",
            "소관부처명": "보건복지부",
            "공포번호": "20445",
            "제개정구분명": "타법개정",
            "소관부처코드": "1352000",
            "id": "806",
            "법령ID": "000187",
            "공동부령정보": "",
            "시행일자": "20250621",
            "공포일자": "20240920",
            "법령약칭명": ""
        },
        {
            "현행연혁코드": "현행",
            "법령일련번호": "272431",
            "자법타법여부": "",
            "법령상세링크": "/DRF/lawService.do?OC=knowhow1&target=eflaw&MST=272431&type=HTML&mobileYn=&efYd=20250621",
            "법령명한글": "장애인 등에 대한 특수교육법 시행규칙",
            "법령구분명": "교육부령",
            "소관부처명": "교육부",
            "공포번호": "00360",
            "제개정구분명": "일부개정",
            "소관부처코드": "1342000",
            "id": "807",
            "법령ID": "010772",
            "공동부령정보": "",
            "시행일자": "20250621",
            "공포일자": "20250620",
            "법령약칭명": "특수교육법 시행규칙"
        },
        {
            "현행연혁코드": "현행",
            "법령일련번호": "267309",
            "자법타법여부": "",
            "법령상세링크": "/DRF/lawService.do?OC=knowhow1&target=eflaw&MST=267309&type=HTML&mobileYn=&efYd=20250621",
            "법령명한글": "장애인 등에 대한 특수교육법",
            "법령구분명": "법률",
            "소관부처명": "교육부",
            "공포번호": "20565",
            "제개정구분명": "일부개정",
            "소관부처코드": "1342000",
            "id": "808",
            "법령ID": "010449",
            "공동부령정보": "",
            "시행일자": "20250621",
            "공포일자": "20241220",
            "법령약칭명": "특수교육법"
        },
        {
            "현행연혁코드": "연혁",
            "법령일련번호": "267317",
            "자법타법여부": "",
            "법령상세링크": "/DRF/lawService.do?OC=knowhow1&target=eflaw&MST=267317&type=HTML&mobileYn=&efYd=20250621",
            "법령명한글": "자치입법권 강화 및 지방자율성 제고를 위한 농어촌정비법 등 10개 법률의 일부개정에 관한 법률",
            "법령구분명": "법률",
            "소관부처명": "",
            "공포번호": "20581",
            "제개정구분명": "일괄개정",
            "소관부처코드": "",
            "id": "809",
            "법령ID": "014790",
            "공동부령정보": "",
            "시행일자": "20250621",
            "공포일자": "20241220",
            "법령약칭명": ""
        },
        {
            "현행연혁코드": "현행",
            "법령일련번호": "272517",
            "자법타법여부": "",
            "법령상세링크": "/DRF/lawService.do?OC=knowhow1&target=eflaw&MST=272517&type=HTML&mobileYn=&efYd=20250621",
            "법령명한글": "자동차손해배상 보장법 시행령",
            "법령구분명": "대통령령",
            "소관부처명": "국토교통부",
            "공포번호": "35597",
            "제개정구분명": "타법개정",
            "소관부처코드": "1613000",
            "id": "810",
            "법령ID": "004594",
            "공동부령정보": "",
            "시행일자": "20250621",
            "공포일자": "20250620",
            "법령약칭명": "자동차손배법 시행령"
        },
        {
            "현행연혁코드": "현행",
            "법령일련번호": "272545",
            "자법타법여부": "",
            "법령상세링크": "/DRF/lawService.do?OC=knowhow1&target=eflaw&MST=272545&type=HTML&mobileYn=&efYd=20250621",
            "법령명한글": "의료유사업자에 관한 규칙",
            "법령구분명": "보건복지부령",
            "소관부처명": "보건복지부",
            "공포번호": "01118",
            "제개정구분명": "타법개정",
            "소관부처코드": "1352000",
            "id": "811",
            "법령ID": "006137",
            "공동부령정보": "",
            "시행일자": "20250621",
            "공포일자": "20250620",
            "법령약칭명": ""
        },
        {
            "현행연혁코드": "연혁",
            "법령일련번호": "272515",
            "자법타법여부": "",
            "법령상세링크": "/DRF/lawService.do?OC=knowhow1&target=eflaw&MST=272515&type=HTML&mobileYn=&efYd=20250621",
            "법령명한글": "의료사고 피해구제 및 의료분쟁 조정 등에 관한 법률 시행령",
            "법령구분명": "대통령령",
            "소관부처명": "보건복지부",
            "공포번호": "35597",
            "제개정구분명": "타법개정",
            "소관부처코드": "1352000",
            "id": "812",
            "법령ID": "011585",
            "공동부령정보": "",
            "시행일자": "20250621",
            "공포일자": "20250620",
            "법령약칭명": "의료분쟁조정법 시행령"
        },
        {
            "현행연혁코드": "현행",
            "법령일련번호": "265473",
            "자법타법여부": "",
            "법령상세링크": "/DRF/lawService.do?OC=knowhow1&target=eflaw&MST=265473&type=HTML&mobileYn=&efYd=20250621",
            "법령명한글": "의료사고 피해구제 및 의료분쟁 조정 등에 관한 법률",
            "법령구분명": "법률",
            "소관부처명": "보건복지부",
            "공포번호": "20445",
            "제개정구분명": "타법개정",
            "소관부처코드": "1352000",
            "id": "813",
            "법령ID": "011374",
            "공동부령정보": "",
            "시행일자": "20250621",
            "공포일자": "20240920",
            "법령약칭명": "의료분쟁조정법"
        },
        {
            "현행연혁코드": "현행",
            "법령일련번호": "272513",
            "자법타법여부": "",
            "법령상세링크": "/DRF/lawService.do?OC=knowhow1&target=eflaw&MST=272513&type=HTML&mobileYn=&efYd=20250621",
            "법령명한글": "의료법 시행령",
            "법령구분명": "대통령령",
            "소관부처명": "보건복지부,질병관리청",
            "공포번호": "35597",
            "제개정구분명": "타법개정",
            "소관부처코드": "1352000,1790387",
            "id": "814",
            "법령ID": "004482",
            "공동부령정보": "",
            "시행일자": "20250621",
            "공포일자": "20250620",
            "법령약칭명": ""
        },
        {
            "현행연혁코드": "연혁",
            "법령일련번호": "271467",
            "자법타법여부": "",
            "법령상세링크": "/DRF/lawService.do?OC=knowhow1&target=eflaw&MST=271467&type=HTML&mobileYn=&efYd=20250621",
            "법령명한글": "의료법 시행령",
            "법령구분명": "대통령령",
            "소관부처명": "보건복지부,질병관리청",
            "공포번호": "35573",
            "제개정구분명": "일부개정",
            "소관부처코드": "1352000,1790387",
            "id": "815",
            "법령ID": "004482",
            "공동부령정보": "",
            "시행일자": "20250621",
            "공포일자": "20250602",
            "법령약칭명": ""
        },
        {
            "현행연혁코드": "현행",
            "법령일련번호": "272423",
            "자법타법여부": "",
            "법령상세링크": "/DRF/lawService.do?OC=knowhow1&target=eflaw&MST=272423&type=HTML&mobileYn=&efYd=20250621",
            "법령명한글": "의료법 시행규칙",
            "법령구분명": "보건복지부령",
            "소관부처명": "보건복지부,질병관리청",
            "공포번호": "01116",
            "제개정구분명": "일부개정",
            "소관부처코드": "1352000,1790387",
            "id": "816",
            "법령ID": "007863",
            "공동부령정보": "",
            "시행일자": "20250621",
            "공포일자": "20250620",
            "법령약칭명": ""
        },
        {
            "현행연혁코드": "연혁",
            "법령일련번호": "267397",
            "자법타법여부": "",
            "법령상세링크": "/DRF/lawService.do?OC=knowhow1&target=eflaw&MST=267397&type=HTML&mobileYn=&efYd=20250621",
            "법령명한글": "의료법",
            "법령구분명": "법률",
            "소관부처명": "보건복지부,질병관리청",
            "공포번호": "20593",
            "제개정구분명": "일부개정",
            "소관부처코드": "1352000,1790387",
            "id": "817",
            "법령ID": "001788",
            "공동부령정보": "",
            "시행일자": "20250621",
            "공포일자": "20241220",
            "법령약칭명": ""
        },
        {
            "현행연혁코드": "연혁",
            "법령일련번호": "265471",
            "자법타법여부": "",
            "법령상세링크": "/DRF/lawService.do?OC=knowhow1&target=eflaw&MST=265471&type=HTML&mobileYn=&efYd=20250621",
            "법령명한글": "의료법",
            "법령구분명": "법률",
            "소관부처명": "보건복지부,질병관리청",
            "공포번호": "20445",
            "제개정구분명": "타법개정",
            "소관부처코드": "1352000,1790387",
            "id": "818",
            "법령ID": "001788",
            "공동부령정보": "",
            "시행일자": "20250621",
            "공포일자": "20240920",
            "법령약칭명": ""
        },
        {
            "현행연혁코드": "현행",
            "법령일련번호": "272549",
            "자법타법여부": "",
            "법령상세링크": "/DRF/lawService.do?OC=knowhow1&target=eflaw&MST=272549&type=HTML&mobileYn=&efYd=20250621",
            "법령명한글": "의료관계 행정처분 규칙",
            "법령구분명": "보건복지부령",
            "소관부처명": "보건복지부",
            "공포번호": "01118",
            "제개정구분명": "타법개정",
            "소관부처코드": "1352000",
            "id": "819",
            "법령ID": "007859",
            "공동부령정보": "",
            "시행일자": "20250621",
            "공포일자": "20250620",
            "법령약칭명": ""
        },
        {
            "현행연혁코드": "연혁",
            "법령일련번호": "265467",
            "자법타법여부": "",
            "법령상세링크": "/DRF/lawService.do?OC=knowhow1&target=eflaw&MST=265467&type=HTML&mobileYn=&efYd=20250621",
            "법령명한글": "응급의료에 관한 법률",
            "법령구분명": "법률",
            "소관부처명": "보건복지부",
            "공포번호": "20445",
            "제개정구분명": "타법개정",
            "소관부처코드": "1352000",
            "id": "820",
            "법령ID": "000218",
            "공동부령정보": "",
            "시행일자": "20250621",
            "공포일자": "20240920",
            "법령약칭명": "응급의료법"
        },
        {
            "현행연혁코드": "현행",
            "법령일련번호": "272511",
            "자법타법여부": "",
            "법령상세링크": "/DRF/lawService.do?OC=knowhow1&target=eflaw&MST=272511&type=HTML&mobileYn=&efYd=20250621",
            "법령명한글": "영유아보육법 시행령",
            "법령구분명": "대통령령",
            "소관부처명": "교육부",
            "공포번호": "35597",
            "제개정구분명": "타법개정",
            "소관부처코드": "1342000",
            "id": "821",
            "법령ID": "004216",
            "공동부령정보": "",
            "시행일자": "20250621",
            "공포일자": "20250620",
            "법령약칭명": ""
        },
        {
            "현행연혁코드": "현행",
            "법령일련번호": "272471",
            "자법타법여부": "",
            "법령상세링크": "/DRF/lawService.do?OC=knowhow1&target=eflaw&MST=272471&type=HTML&mobileYn=&efYd=20250621",
            "법령명한글": "아동학대범죄의 처벌 등에 관한 특례법 시행령",
            "법령구분명": "대통령령",
            "소관부처명": "법무부",
            "공포번호": "35596",
            "제개정구분명": "일부개정",
            "소관부처코드": "1270000",
            "id": "822",
            "법령ID": "012146",
            "공동부령정보": "",
            "시행일자": "20250621",
            "공포일자": "20250620",
            "법령약칭명": "아동학대처벌법 시행령"
        },
        {
            "현행연혁코드": "현행",
            "법령일련번호": "272541",
            "자법타법여부": "",
            "법령상세링크": "/DRF/lawService.do?OC=knowhow1&target=eflaw&MST=272541&type=HTML&mobileYn=&efYd=20250621",
            "법령명한글": "아동학대범죄의 처벌 등에 관한 특례법 시행규칙",
            "법령구분명": "법무부령",
            "소관부처명": "법무부",
            "공포번호": "01100",
            "제개정구분명": "일부개정",
            "소관부처코드": "1270000",
            "id": "823",
            "법령ID": "012148",
            "공동부령정보": "",
            "시행일자": "20250621",
            "공포일자": "20250620",
            "법령약칭명": "아동학대처벌법 시행규칙"
        },
        {
            "현행연혁코드": "연혁",
            "법령일련번호": "267357",
            "자법타법여부": "",
            "법령상세링크": "/DRF/lawService.do?OC=knowhow1&target=eflaw&MST=267357&type=HTML&mobileYn=&efYd=20250621",
            "법령명한글": "아동학대범죄의 처벌 등에 관한 특례법",
            "법령구분명": "법률",
            "소관부처명": "법무부",
            "공포번호": "20576",
            "제개정구분명": "일부개정",
            "소관부처코드": "1270000",
            "id": "824",
            "법령ID": "011997",
            "공동부령정보": "",
            "시행일자": "20250621",
            "공포일자": "20241220",
            "법령약칭명": "아동학대처벌법"
        },
        {
            "현행연혁코드": "현행",
            "법령일련번호": "265465",
            "자법타법여부": "",
            "법령상세링크": "/DRF/lawService.do?OC=knowhow1&target=eflaw&MST=265465&type=HTML&mobileYn=&efYd=20250621",
            "법령명한글": "아동ㆍ청소년의 성보호에 관한 법률",
            "법령구분명": "법률",
            "소관부처명": "여성가족부",
            "공포번호": "20445",
            "제개정구분명": "타법개정",
            "소관부처코드": "1383000",
            "id": "825",
            "법령ID": "002044",
            "공동부령정보": "",
            "시행일자": "20250621",
            "공포일자": "20240920",
            "법령약칭명": "청소년성보호법"
        },
        {
            "현행연혁코드": "연혁",
            "법령일련번호": "272509",
            "자법타법여부": "",
            "법령상세링크": "/DRF/lawService.do?OC=knowhow1&target=eflaw&MST=272509&type=HTML&mobileYn=&efYd=20250621",
            "법령명한글": "아동복지법 시행령",
            "법령구분명": "대통령령",
            "소관부처명": "보건복지부",
            "공포번호": "35597",
            "제개정구분명": "타법개정",
            "소관부처코드": "1352000",
            "id": "826",
            "법령ID": "004124",
            "공동부령정보": "",
            "시행일자": "20250621",
            "공포일자": "20250620",
            "법령약칭명": ""
        },
        {
            "현행연혁코드": "현행",
            "법령일련번호": "271517",
            "자법타법여부": "",
            "법령상세링크": "/DRF/lawService.do?OC=knowhow1&target=eflaw&MST=271517&type=HTML&mobileYn=&efYd=20250621",
            "법령명한글": "아동보호심판규칙",
            "법령구분명": "대법원규칙",
            "소관부처명": "대법원",
            "공포번호": "03213",
            "제개정구분명": "일부개정",
            "소관부처코드": "9740000",
            "id": "827",
            "법령ID": "012140",
            "공동부령정보": "",
            "시행일자": "20250621",
            "공포일자": "20250530",
            "법령약칭명": ""
        },
        {
            "현행연혁코드": "현행",
            "법령일련번호": "272507",
            "자법타법여부": "",
            "법령상세링크": "/DRF/lawService.do?OC=knowhow1&target=eflaw&MST=272507&type=HTML&mobileYn=&efYd=20250621",
            "법령명한글": "수상에서의 수색ㆍ구조 등에 관한 법률 시행령",
            "법령구분명": "대통령령",
            "소관부처명": "해양경찰청",
            "공포번호": "35597",
            "제개정구분명": "타법개정",
            "소관부처코드": "1532000",
            "id": "828",
            "법령ID": "003997",
            "공동부령정보": "",
            "시행일자": "20250621",
            "공포일자": "20250620",
            "법령약칭명": "수상구조법 시행령"
        },
        {
            "현행연혁코드": "현행",
            "법령일련번호": "271455",
            "자법타법여부": "",
            "법령상세링크": "/DRF/lawService.do?OC=knowhow1&target=eflaw&MST=271455&type=HTML&mobileYn=&efYd=20250621",
            "법령명한글": "수상레저안전법 시행령",
            "법령구분명": "대통령령",
            "소관부처명": "해양경찰청",
            "공포번호": "35586",
            "제개정구분명": "일부개정",
            "소관부처코드": "1532000",
            "id": "829",
            "법령ID": "004026",
            "공동부령정보": "",
            "시행일자": "20250621",
            "공포일자": "20250602",
            "법령약칭명": ""
        },
        {
            "현행연혁코드": "현행",
            "법령일련번호": "267437",
            "자법타법여부": "",
            "법령상세링크": "/DRF/lawService.do?OC=knowhow1&target=eflaw&MST=267437&type=HTML&mobileYn=&efYd=20250621",
            "법령명한글": "수상레저안전법",
            "법령구분명": "법률",
            "소관부처명": "해양경찰청",
            "공포번호": "20599",
            "제개정구분명": "일부개정",
            "소관부처코드": "1532000",
            "id": "830",
            "법령ID": "001988",
            "공동부령정보": "",
            "시행일자": "20250621",
            "공포일자": "20241220",
            "법령약칭명": ""
        },
        {
            "현행연혁코드": "현행",
            "법령일련번호": "272429",
            "자법타법여부": "",
            "법령상세링크": "/DRF/lawService.do?OC=knowhow1&target=eflaw&MST=272429&type=HTML&mobileYn=&efYd=20250621",
            "법령명한글": "수목원ㆍ정원의 조성 및 진흥에 관한 법률 시행규칙",
            "법령구분명": "농림축산식품부령",
            "소관부처명": "산림청",
            "공포번호": "00724",
            "제개정구분명": "일부개정",
            "소관부처코드": "1400000",
            "id": "831",
            "법령ID": "009259",
            "공동부령정보": "",
            "시행일자": "20250621",
            "공포일자": "20250620",
            "법령약칭명": "수목원정원법 시행규칙"
        },
        {
            "현행연혁코드": "현행",
            "법령일련번호": "267375",
            "자법타법여부": "",
            "법령상세링크": "/DRF/lawService.do?OC=knowhow1&target=eflaw&MST=267375&type=HTML&mobileYn=&efYd=20250621",
            "법령명한글": "수목원ㆍ정원의 조성 및 진흥에 관한 법률",
            "법령구분명": "법률",
            "소관부처명": "산림청",
            "공포번호": "20581",
            "제개정구분명": "타법개정",
            "소관부처코드": "1400000",
            "id": "832",
            "법령ID": "009201",
            "공동부령정보": "",
            "시행일자": "20250621",
            "공포일자": "20241220",
            "법령약칭명": "수목원정원법"
        },
        {
            "현행연혁코드": "현행",
            "법령일련번호": "272505",
            "자법타법여부": "",
            "법령상세링크": "/DRF/lawService.do?OC=knowhow1&target=eflaw&MST=272505&type=HTML&mobileYn=&efYd=20250621",
            "법령명한글": "소방기본법 시행령",
            "법령구분명": "대통령령",
            "소관부처명": "소방청",
            "공포번호": "35597",
            "제개정구분명": "타법개정",
            "소관부처코드": "1661000",
            "id": "833",
            "법령ID": "009696",
            "공동부령정보": "",
            "시행일자": "20250621",
            "공포일자": "20250620",
            "법령약칭명": ""
        },
        {
            "현행연혁코드": "현행",
            "법령일련번호": "267333",
            "자법타법여부": "",
            "법령상세링크": "/DRF/lawService.do?OC=knowhow1&target=eflaw&MST=267333&type=HTML&mobileYn=&efYd=20250621",
            "법령명한글": "소나무재선충병 방제특별법",
            "법령구분명": "법률",
            "소관부처명": "산림청",
            "공포번호": "20581",
            "제개정구분명": "타법개정",
            "소관부처코드": "1400000",
            "id": "834",
            "법령ID": "009940",
            "공동부령정보": "",
            "시행일자": "20250621",
            "공포일자": "20241220",
            "법령약칭명": "재선충방제법"
        },
        {
            "현행연혁코드": "현행",
            "법령일련번호": "271287",
            "자법타법여부": "",
            "법령상세링크": "/DRF/lawService.do?OC=knowhow1&target=eflaw&MST=271287&type=HTML&mobileYn=&efYd=20250621",
            "법령명한글": "성폭력범죄의 처벌 등에 관한 특례법 시행령",
            "법령구분명": "대통령령",
            "소관부처명": "법무부",
            "공포번호": "35539",
            "제개정구분명": "일부개정",
            "소관부처코드": "1270000",
            "id": "835",
            "법령ID": "011377",
            "공동부령정보": "",
            "시행일자": "20250621",
            "공포일자": "20250527",
            "법령약칭명": "성폭력처벌법 시행령"
        },
        {
            "현행연혁코드": "현행",
            "법령일련번호": "267313",
            "자법타법여부": "",
            "법령상세링크": "/DRF/lawService.do?OC=knowhow1&target=eflaw&MST=267313&type=HTML&mobileYn=&efYd=20250621",
            "법령명한글": "성폭력범죄의 처벌 등에 관한 특례법",
            "법령구분명": "법률",
            "소관부처명": "법무부",
            "공포번호": "20575",
            "제개정구분명": "일부개정",
            "소관부처코드": "1270000",
            "id": "836",
            "법령ID": "011187",
            "공동부령정보": "",
            "시행일자": "20250621",
            "공포일자": "20241220",
            "법령약칭명": "성폭력처벌법"
        },
        {
            "현행연혁코드": "현행",
            "법령일련번호": "272503",
            "자법타법여부": "",
            "법령상세링크": "/DRF/lawService.do?OC=knowhow1&target=eflaw&MST=272503&type=HTML&mobileYn=&efYd=20250621",
            "법령명한글": "성폭력방지 및 피해자보호 등에 관한 법률 시행령",
            "법령구분명": "대통령령",
            "소관부처명": "여성가족부",
            "공포번호": "35597",
            "제개정구분명": "타법개정",
            "소관부처코드": "1383000",
            "id": "837",
            "법령ID": "011319",
            "공동부령정보": "",
            "시행일자": "20250621",
            "공포일자": "20250620",
            "법령약칭명": "성폭력방지법 시행령"
        },
        {
            "현행연혁코드": "현행",
            "법령일련번호": "271413",
            "자법타법여부": "",
            "법령상세링크": "/DRF/lawService.do?OC=knowhow1&target=eflaw&MST=271413&type=HTML&mobileYn=&efYd=20250621",
            "법령명한글": "선박교통관제에 관한 법률 시행령",
            "법령구분명": "대통령령",
            "소관부처명": "해양경찰청",
            "공포번호": "35585",
            "제개정구분명": "일부개정",
            "소관부처코드": "1532000",
            "id": "838",
            "법령ID": "013767",
            "공동부령정보": "",
            "시행일자": "20250621",
            "공포일자": "20250602",
            "법령약칭명": "선박교통관제법 시행령"
        },
        {
            "현행연혁코드": "현행",
            "법령일련번호": "271551",
            "자법타법여부": "",
            "법령상세링크": "/DRF/lawService.do?OC=knowhow1&target=eflaw&MST=271551&type=HTML&mobileYn=&efYd=20250621",
            "법령명한글": "선박교통관제에 관한 법률 시행규칙",
            "법령구분명": "해양수산부령",
            "소관부처명": "해양경찰청",
            "공포번호": "00740",
            "제개정구분명": "일부개정",
            "소관부처코드": "1532000",
            "id": "839",
            "법령ID": "013772",
            "공동부령정보": "",
            "시행일자": "20250621",
            "공포일자": "20250609",
            "법령약칭명": "선박교통관제법 시행규칙"
        },
        {
            "현행연혁코드": "현행",
            "법령일련번호": "267401",
            "자법타법여부": "",
            "법령상세링크": "/DRF/lawService.do?OC=knowhow1&target=eflaw&MST=267401&type=HTML&mobileYn=&efYd=20250621",
            "법령명한글": "선박교통관제에 관한 법률",
            "법령구분명": "법률",
            "소관부처명": "해양경찰청",
            "공포번호": "20598",
            "제개정구분명": "일부개정",
            "소관부처코드": "1532000",
            "id": "840",
            "법령ID": "013617",
            "공동부령정보": "",
            "시행일자": "20250621",
            "공포일자": "20241220",
            "법령약칭명": "선박교통관제법"
        },
        {
            "현행연혁코드": "현행",
            "법령일련번호": "265463",
            "자법타법여부": "",
            "법령상세링크": "/DRF/lawService.do?OC=knowhow1&target=eflaw&MST=265463&type=HTML&mobileYn=&efYd=20250621",
            "법령명한글": "새만금사업 추진 및 지원에 관한 특별법",
            "법령구분명": "법률",
            "소관부처명": "국토교통부",
            "공포번호": "20445",
            "제개정구분명": "타법개정",
            "소관부처코드": "1613000",
            "id": "841",
            "법령ID": "011724",
            "공동부령정보": "",
            "시행일자": "20250621",
            "공포일자": "20240920",
            "법령약칭명": "새만금사업법"
        },
        {
            "현행연혁코드": "현행",
            "법령일련번호": "272501",
            "자법타법여부": "",
            "법령상세링크": "/DRF/lawService.do?OC=knowhow1&target=eflaw&MST=272501&type=HTML&mobileYn=&efYd=20250621",
            "법령명한글": "산업재해보상보험법 시행령",
            "법령구분명": "대통령령",
            "소관부처명": "고용노동부",
            "공포번호": "35597",
            "제개정구분명": "타법개정",
            "소관부처코드": "1492000",
            "id": "842",
            "법령ID": "003793",
            "공동부령정보": "",
            "시행일자": "20250621",
            "공포일자": "20250620",
            "법령약칭명": ""
        },
        {
            "현행연혁코드": "현행",
            "법령일련번호": "272427",
            "자법타법여부": "",
            "법령상세링크": "/DRF/lawService.do?OC=knowhow1&target=eflaw&MST=272427&type=HTML&mobileYn=&efYd=20250621",
            "법령명한글": "산업재해보상보험법 시행규칙",
            "법령구분명": "고용노동부령",
            "소관부처명": "고용노동부",
            "공포번호": "00445",
            "제개정구분명": "일부개정",
            "소관부처코드": "1492000",
            "id": "843",
            "법령ID": "007373",
            "공동부령정보": "",
            "시행일자": "20250621",
            "공포일자": "20250620",
            "법령약칭명": ""
        },
        {
            "현행연혁코드": "현행",
            "법령일련번호": "272499",
            "자법타법여부": "",
            "법령상세링크": "/DRF/lawService.do?OC=knowhow1&target=eflaw&MST=272499&type=HTML&mobileYn=&efYd=20250621",
            "법령명한글": "산업안전보건법 시행령",
            "법령구분명": "대통령령",
            "소관부처명": "고용노동부",
            "공포번호": "35597",
            "제개정구분명": "타법개정",
            "소관부처코드": "1492000",
            "id": "844",
            "법령ID": "003786",
            "공동부령정보": "",
            "시행일자": "20250621",
            "공포일자": "20250620",
            "법령약칭명": ""
        },
        {
            "현행연혁코드": "현행",
            "법령일련번호": "271429",
            "자법타법여부": "",
            "법령상세링크": "/DRF/lawService.do?OC=knowhow1&target=eflaw&MST=271429&type=HTML&mobileYn=&efYd=20250621",
            "법령명한글": "산업교육진흥 및 산학연협력촉진에 관한 법률 시행령",
            "법령구분명": "대통령령",
            "소관부처명": "교육부",
            "공포번호": "35555",
            "제개정구분명": "일부개정",
            "소관부처코드": "1342000",
            "id": "845",
            "법령ID": "003777",
            "공동부령정보": "",
            "시행일자": "20250621",
            "공포일자": "20250602",
            "법령약칭명": "산학협력법 시행령"
        },
        {
            "현행연혁코드": "현행",
            "법령일련번호": "272425",
            "자법타법여부": "",
            "법령상세링크": "/DRF/lawService.do?OC=knowhow1&target=eflaw&MST=272425&type=HTML&mobileYn=&efYd=20250621",
            "법령명한글": "산업교육진흥 및 산학연협력촉진에 관한 법률 시행규칙",
            "법령구분명": "교육부령",
            "소관부처명": "교육부",
            "공포번호": "00361",
            "제개정구분명": "일부개정",
            "소관부처코드": "1342000",
            "id": "846",
            "법령ID": "007354",
            "공동부령정보": "",
            "시행일자": "20250621",
            "공포일자": "20250620",
            "법령약칭명": "산학협력법 시행규칙"
        },
        {
            "현행연혁코드": "현행",
            "법령일련번호": "267351",
            "자법타법여부": "",
            "법령상세링크": "/DRF/lawService.do?OC=knowhow1&target=eflaw&MST=267351&type=HTML&mobileYn=&efYd=20250621",
            "법령명한글": "산업교육진흥 및 산학연협력촉진에 관한 법률",
            "법령구분명": "법률",
            "소관부처명": "교육부",
            "공포번호": "20563",
            "제개정구분명": "일부개정",
            "소관부처코드": "1342000",
            "id": "847",
            "법령ID": "000865",
            "공동부령정보": "",
            "시행일자": "20250621",
            "공포일자": "20241220",
            "법령약칭명": "산학협력법"
        },
        {
            "현행연혁코드": "현행",
            "법령일련번호": "267329",
            "자법타법여부": "",
            "법령상세링크": "/DRF/lawService.do?OC=knowhow1&target=eflaw&MST=267329&type=HTML&mobileYn=&efYd=20250621",
            "법령명한글": "산림문화ㆍ휴양에 관한 법률",
            "법령구분명": "법률",
            "소관부처명": "산림청",
            "공포번호": "20581",
            "제개정구분명": "타법개정",
            "소관부처코드": "1400000",
            "id": "848",
            "법령ID": "010004",
            "공동부령정보": "",
            "시행일자": "20250621",
            "공포일자": "20241220",
            "법령약칭명": "산림휴양법"
        },
        {
            "현행연혁코드": "현행",
            "법령일련번호": "271497",
            "자법타법여부": "",
            "법령상세링크": "/DRF/lawService.do?OC=knowhow1&target=eflaw&MST=271497&type=HTML&mobileYn=&efYd=20250621",
            "법령명한글": "사회보장기본법 시행령",
            "법령구분명": "대통령령",
            "소관부처명": "보건복지부",
            "공포번호": "35572",
            "제개정구분명": "일부개정",
            "소관부처코드": "1352000",
            "id": "849",
            "법령ID": "003754",
            "공동부령정보": "",
            "시행일자": "20250621",
            "공포일자": "20250602",
            "법령약칭명": ""
        },
        {
            "현행연혁코드": "현행",
            "법령일련번호": "267367",
            "자법타법여부": "",
            "법령상세링크": "/DRF/lawService.do?OC=knowhow1&target=eflaw&MST=267367&type=HTML&mobileYn=&efYd=20250621",
            "법령명한글": "사회보장기본법",
            "법령구분명": "법률",
            "소관부처명": "보건복지부",
            "공포번호": "20591",
            "제개정구분명": "일부개정",
            "소관부처코드": "1352000",
            "id": "850",
            "법령ID": "000204",
            "공동부령정보": "",
            "시행일자": "20250621",
            "공포일자": "20241220",
            "법령약칭명": ""
        },
        {
            "현행연혁코드": "현행",
            "법령일련번호": "271435",
            "자법타법여부": "",
            "법령상세링크": "/DRF/lawService.do?OC=knowhow1&target=eflaw&MST=271435&type=HTML&mobileYn=&efYd=20250621",
            "법령명한글": "북한이탈주민의 보호 및 정착지원에 관한 법률 시행령",
            "법령구분명": "대통령령",
            "소관부처명": "통일부",
            "공포번호": "35557",
            "제개정구분명": "일부개정",
            "소관부처코드": "1250000",
            "id": "851",
            "법령ID": "003693",
            "공동부령정보": "",
            "시행일자": "20250621",
            "공포일자": "20250602",
            "법령약칭명": "북한이탈주민법 시행령"
        },
        {
            "현행연혁코드": "현행",
            "법령일련번호": "267311",
            "자법타법여부": "",
            "법령상세링크": "/DRF/lawService.do?OC=knowhow1&target=eflaw&MST=267311&type=HTML&mobileYn=&efYd=20250621",
            "법령명한글": "북한이탈주민의 보호 및 정착지원에 관한 법률",
            "법령구분명": "법률",
            "소관부처명": "통일부",
            "공포번호": "20574",
            "제개정구분명": "일부개정",
            "소관부처코드": "1250000",
            "id": "852",
            "법령ID": "001432",
            "공동부령정보": "",
            "시행일자": "20250621",
            "공포일자": "20241220",
            "법령약칭명": "북한이탈주민법"
        },
        {
            "현행연혁코드": "연혁",
            "법령일련번호": "272497",
            "자법타법여부": "",
            "법령상세링크": "/DRF/lawService.do?OC=knowhow1&target=eflaw&MST=272497&type=HTML&mobileYn=&efYd=20250621",
            "법령명한글": "부가가치세법 시행령",
            "법령구분명": "대통령령",
            "소관부처명": "기획재정부",
            "공포번호": "35597",
            "제개정구분명": "타법개정",
            "소관부처코드": "1051000",
            "id": "853",
            "법령ID": "003666",
            "공동부령정보": "",
            "시행일자": "20250621",
            "공포일자": "20250620",
            "법령약칭명": ""
        },
        {
            "현행연혁코드": "현행",
            "법령일련번호": "265461",
            "자법타법여부": "",
            "법령상세링크": "/DRF/lawService.do?OC=knowhow1&target=eflaw&MST=265461&type=HTML&mobileYn=&efYd=20250621",
            "법령명한글": "보건의료인력지원법",
            "법령구분명": "법률",
            "소관부처명": "보건복지부",
            "공포번호": "20445",
            "제개정구분명": "타법개정",
            "소관부처코드": "1352000",
            "id": "854",
            "법령ID": "013470",
            "공동부령정보": "",
            "시행일자": "20250621",
            "공포일자": "20240920",
            "법령약칭명": ""
        },
        {
            "현행연혁코드": "현행",
            "법령일련번호": "267417",
            "자법타법여부": "",
            "법령상세링크": "/DRF/lawService.do?OC=knowhow1&target=eflaw&MST=267417&type=HTML&mobileYn=&efYd=20250621",
            "법령명한글": "보건의료기본법",
            "법령구분명": "법률",
            "소관부처명": "보건복지부,질병관리청",
            "공포번호": "20589",
            "제개정구분명": "일부개정",
            "소관부처코드": "1352000,1790387",
            "id": "855",
            "법령ID": "002029",
            "공동부령정보": "",
            "시행일자": "20250621",
            "공포일자": "20241220",
            "법령약칭명": ""
        },
        {
            "현행연혁코드": "연혁",
            "법령일련번호": "265459",
            "자법타법여부": "",
            "법령상세링크": "/DRF/lawService.do?OC=knowhow1&target=eflaw&MST=265459&type=HTML&mobileYn=&efYd=20250621",
            "법령명한글": "보건의료기본법",
            "법령구분명": "법률",
            "소관부처명": "보건복지부,질병관리청",
            "공포번호": "20445",
            "제개정구분명": "타법개정",
            "소관부처코드": "1352000,1790387",
            "id": "856",
            "법령ID": "002029",
            "공동부령정보": "",
            "시행일자": "20250621",
            "공포일자": "20240920",
            "법령약칭명": ""
        },
        {
            "현행연혁코드": "현행",
            "법령일련번호": "272495",
            "자법타법여부": "",
            "법령상세링크": "/DRF/lawService.do?OC=knowhow1&target=eflaw&MST=272495&type=HTML&mobileYn=&efYd=20250621",
            "법령명한글": "범죄피해자 보호법 시행령",
            "법령구분명": "대통령령",
            "소관부처명": "법무부",
            "공포번호": "35597",
            "제개정구분명": "타법개정",
            "소관부처코드": "1270000",
            "id": "857",
            "법령ID": "010201",
            "공동부령정보": "",
            "시행일자": "20250621",
            "공포일자": "20250620",
            "법령약칭명": ""
        },
        {
            "현행연혁코드": "현행",
            "법령일련번호": "272453",
            "자법타법여부": "",
            "법령상세링크": "/DRF/lawService.do?OC=knowhow1&target=eflaw&MST=272453&type=HTML&mobileYn=&efYd=20250621",
            "법령명한글": "모자보건법 시행령",
            "법령구분명": "대통령령",
            "소관부처명": "보건복지부",
            "공포번호": "35597",
            "제개정구분명": "타법개정",
            "소관부처코드": "1352000",
            "id": "858",
            "법령ID": "003476",
            "공동부령정보": "",
            "시행일자": "20250621",
            "공포일자": "20250620",
            "법령약칭명": ""
        },
        {
            "현행연혁코드": "현행",
            "법령일련번호": "267327",
            "자법타법여부": "",
            "법령상세링크": "/DRF/lawService.do?OC=knowhow1&target=eflaw&MST=267327&type=HTML&mobileYn=&efYd=20250621",
            "법령명한글": "말산업 육성법",
            "법령구분명": "법률",
            "소관부처명": "농림축산식품부",
            "공포번호": "20581",
            "제개정구분명": "타법개정",
            "소관부처코드": "1543000",
            "id": "859",
            "법령ID": "011351",
            "공동부령정보": "",
            "시행일자": "20250621",
            "공포일자": "20241220",
            "법령약칭명": ""
        },
        {
            "현행연혁코드": "현행",
            "법령일련번호": "267325",
            "자법타법여부": "",
            "법령상세링크": "/DRF/lawService.do?OC=knowhow1&target=eflaw&MST=267325&type=HTML&mobileYn=&efYd=20250621",
            "법령명한글": "동물보호법",
            "법령구분명": "법률",
            "소관부처명": "농림축산식품부",
            "공포번호": "20581",
            "제개정구분명": "타법개정",
            "소관부처코드": "1543000",
            "id": "860",
            "법령ID": "000412",
            "공동부령정보": "",
            "시행일자": "20250621",
            "공포일자": "20241220",
            "법령약칭명": ""
        },
        {
            "현행연혁코드": "현행",
            "법령일련번호": "267363",
            "자법타법여부": "",
            "법령상세링크": "/DRF/lawService.do?OC=knowhow1&target=eflaw&MST=267363&type=HTML&mobileYn=&efYd=20250621",
            "법령명한글": "도시와 농어촌 간의 교류촉진에 관한 법률",
            "법령구분명": "법률",
            "소관부처명": "농림축산식품부,해양수산부",
            "공포번호": "20580",
            "제개정구분명": "일부개정",
            "소관부처코드": "1192000,1543000",
            "id": "861",
            "법령ID": "010598",
            "공동부령정보": "",
            "시행일자": "20250621",
            "공포일자": "20241220",
            "법령약칭명": "도농교류법"
        },
        {
            "현행연혁코드": "현행",
            "법령일련번호": "267323",
            "자법타법여부": "",
            "법령상세링크": "/DRF/lawService.do?OC=knowhow1&target=eflaw&MST=267323&type=HTML&mobileYn=&efYd=20250621",
            "법령명한글": "도시숲 등의 조성 및 관리에 관한 법률",
            "법령구분명": "법률",
            "소관부처명": "산림청",
            "공포번호": "20581",
            "제개정구분명": "타법개정",
            "소관부처코드": "1400000",
            "id": "862",
            "법령ID": "013794",
            "공동부령정보": "",
            "시행일자": "20250621",
            "공포일자": "20241220",
            "법령약칭명": "도시숲법"
        },
        {
            "현행연혁코드": "현행",
            "법령일련번호": "267321",
            "자법타법여부": "",
            "법령상세링크": "/DRF/lawService.do?OC=knowhow1&target=eflaw&MST=267321&type=HTML&mobileYn=&efYd=20250621",
            "법령명한글": "도시농업의 육성 및 지원에 관한 법률",
            "법령구분명": "법률",
            "소관부처명": "농림축산식품부",
            "공포번호": "20581",
            "제개정구분명": "타법개정",
            "소관부처코드": "1543000",
            "id": "863",
            "법령ID": "011494",
            "공동부령정보": "",
            "시행일자": "20250621",
            "공포일자": "20241220",
            "법령약칭명": "도시농업법"
        },
        {
            "현행연혁코드": "현행",
            "법령일련번호": "272451",
            "자법타법여부": "",
            "법령상세링크": "/DRF/lawService.do?OC=knowhow1&target=eflaw&MST=272451&type=HTML&mobileYn=&efYd=20250621",
            "법령명한글": "도로명주소법 시행령",
            "법령구분명": "대통령령",
            "소관부처명": "행정안전부",
            "공포번호": "35597",
            "제개정구분명": "타법개정",
            "소관부처코드": "1741000",
            "id": "864",
            "법령ID": "010422",
            "공동부령정보": "",
            "시행일자": "20250621",
            "공포일자": "20250620",
            "법령약칭명": ""
        },
        {
            "현행연혁코드": "현행",
            "법령일련번호": "267319",
            "자법타법여부": "",
            "법령상세링크": "/DRF/lawService.do?OC=knowhow1&target=eflaw&MST=267319&type=HTML&mobileYn=&efYd=20250621",
            "법령명한글": "농어촌정비법",
            "법령구분명": "법률",
            "소관부처명": "농림축산식품부,해양수산부",
            "공포번호": "20581",
            "제개정구분명": "타법개정",
            "소관부처코드": "1192000,1543000",
            "id": "865",
            "법령ID": "000478",
            "공동부령정보": "",
            "시행일자": "20250621",
            "공포일자": "20241220",
            "법령약칭명": ""
        },
        {
            "현행연혁코드": "연혁",
            "법령일련번호": "272449",
            "자법타법여부": "",
            "법령상세링크": "/DRF/lawService.do?OC=knowhow1&target=eflaw&MST=272449&type=HTML&mobileYn=&efYd=20250621",
            "법령명한글": "노인장기요양보험법 시행령",
            "법령구분명": "대통령령",
            "소관부처명": "보건복지부",
            "공포번호": "35597",
            "제개정구분명": "타법개정",
            "소관부처코드": "1352000",
            "id": "866",
            "법령ID": "010526",
            "공동부령정보": "",
            "시행일자": "20250621",
            "공포일자": "20250620",
            "법령약칭명": ""
        },
        {
            "현행연혁코드": "현행",
            "법령일련번호": "272547",
            "자법타법여부": "",
            "법령상세링크": "/DRF/lawService.do?OC=knowhow1&target=eflaw&MST=272547&type=HTML&mobileYn=&efYd=20250621",
            "법령명한글": "노인장기요양보험법 시행규칙",
            "법령구분명": "보건복지부령",
            "소관부처명": "보건복지부",
            "공포번호": "01118",
            "제개정구분명": "타법개정",
            "소관부처코드": "1352000",
            "id": "867",
            "법령ID": "010537",
            "공동부령정보": "",
            "시행일자": "20250621",
            "공포일자": "20250620",
            "법령약칭명": ""
        },
        {
            "현행연혁코드": "현행",
            "법령일련번호": "267387",
            "자법타법여부": "",
            "법령상세링크": "/DRF/lawService.do?OC=knowhow1&target=eflaw&MST=267387&type=HTML&mobileYn=&efYd=20250621",
            "법령명한글": "노인장기요양보험법",
            "법령구분명": "법률",
            "소관부처명": "보건복지부",
            "공포번호": "20587",
            "제개정구분명": "일부개정",
            "소관부처코드": "1352000",
            "id": "868",
            "법령ID": "010436",
            "공동부령정보": "",
            "시행일자": "20250621",
            "공포일자": "20241220",
            "법령약칭명": ""
        },
        {
            "현행연혁코드": "현행",
            "법령일련번호": "267435",
            "자법타법여부": "",
            "법령상세링크": "/DRF/lawService.do?OC=knowhow1&target=eflaw&MST=267435&type=HTML&mobileYn=&efYd=20250621",
            "법령명한글": "낚시 관리 및 육성법",
            "법령구분명": "법률",
            "소관부처명": "해양수산부",
            "공포번호": "20597",
            "제개정구분명": "일부개정",
            "소관부처코드": "1192000",
            "id": "869",
            "법령ID": "011350",
            "공동부령정보": "",
            "시행일자": "20250621",
            "공포일자": "20241220",
            "법령약칭명": "낚시관리법"
        },
        {
            "현행연혁코드": "현행",
            "법령일련번호": "272447",
            "자법타법여부": "",
            "법령상세링크": "/DRF/lawService.do?OC=knowhow1&target=eflaw&MST=272447&type=HTML&mobileYn=&efYd=20250621",
            "법령명한글": "군보건의료에 관한 법률 시행령",
            "법령구분명": "대통령령",
            "소관부처명": "국방부",
            "공포번호": "35597",
            "제개정구분명": "타법개정",
            "소관부처코드": "1290000",
            "id": "870",
            "법령ID": "011695",
            "공동부령정보": "",
            "시행일자": "20250621",
            "공포일자": "20250620",
            "법령약칭명": "군보건의료법 시행령"
        },
        {
            "현행연혁코드": "현행",
            "법령일련번호": "272445",
            "자법타법여부": "",
            "법령상세링크": "/DRF/lawService.do?OC=knowhow1&target=eflaw&MST=272445&type=HTML&mobileYn=&efYd=20250621",
            "법령명한글": "국민건강증진법 시행령",
            "법령구분명": "대통령령",
            "소관부처명": "보건복지부,질병관리청",
            "공포번호": "35597",
            "제개정구분명": "타법개정",
            "소관부처코드": "1352000,1790387",
            "id": "871",
            "법령ID": "002814",
            "공동부령정보": "",
            "시행일자": "20250621",
            "공포일자": "20250620",
            "법령약칭명": ""
        },
        {
            "현행연혁코드": "현행",
            "법령일련번호": "272443",
            "자법타법여부": "",
            "법령상세링크": "/DRF/lawService.do?OC=knowhow1&target=eflaw&MST=272443&type=HTML&mobileYn=&efYd=20250621",
            "법령명한글": "국민건강보험법 시행령",
            "법령구분명": "대통령령",
            "소관부처명": "보건복지부",
            "공포번호": "35597",
            "제개정구분명": "타법개정",
            "소관부처코드": "1352000",
            "id": "872",
            "법령ID": "002813",
            "공동부령정보": "",
            "시행일자": "20250621",
            "공포일자": "20250620",
            "법령약칭명": ""
        },
        {
            "현행연혁코드": "현행",
            "법령일련번호": "272441",
            "자법타법여부": "",
            "법령상세링크": "/DRF/lawService.do?OC=knowhow1&target=eflaw&MST=272441&type=HTML&mobileYn=&efYd=20250621",
            "법령명한글": "국립국가폭력트라우마치유센터의 설립 및 운영에 관한 법률 시행령",
            "법령구분명": "대통령령",
            "소관부처명": "행정안전부",
            "공포번호": "35597",
            "제개정구분명": "타법개정",
            "소관부처코드": "1741000",
            "id": "873",
            "법령ID": "014288",
            "공동부령정보": "",
            "시행일자": "20250621",
            "공포일자": "20250620",
            "법령약칭명": "트라우마치유센터법 시행령"
        },
        {
            "현행연혁코드": "현행",
            "법령일련번호": "272527",
            "자법타법여부": "",
            "법령상세링크": "/DRF/lawService.do?OC=knowhow1&target=eflaw&MST=272527&type=HTML&mobileYn=&efYd=20250621",
            "법령명한글": "국가과학기술 경쟁력 강화를 위한 이공계지원 특별법 시행령",
            "법령구분명": "대통령령",
            "소관부처명": "과학기술정보통신부",
            "공포번호": "35595",
            "제개정구분명": "일부개정",
            "소관부처코드": "1721000",
            "id": "874",
            "법령ID": "009811",
            "공동부령정보": "",
            "시행일자": "20250621",
            "공포일자": "20250620",
            "법령약칭명": "이공계지원법 시행령"
        },
        {
            "현행연혁코드": "연혁",
            "법령일련번호": "267345",
            "자법타법여부": "",
            "법령상세링크": "/DRF/lawService.do?OC=knowhow1&target=eflaw&MST=267345&type=HTML&mobileYn=&efYd=20250621",
            "법령명한글": "국가과학기술 경쟁력 강화를 위한 이공계지원 특별법",
            "법령구분명": "법률",
            "소관부처명": "과학기술정보통신부",
            "공포번호": "20570",
            "제개정구분명": "일부개정",
            "소관부처코드": "1721000",
            "id": "875",
            "법령ID": "009677",
            "공동부령정보": "",
            "시행일자": "20250621",
            "공포일자": "20241220",
            "법령약칭명": "이공계지원법"
        },
        {
            "현행연혁코드": "연혁",
            "법령일련번호": "265457",
            "자법타법여부": "",
            "법령상세링크": "/DRF/lawService.do?OC=knowhow1&target=eflaw&MST=265457&type=HTML&mobileYn=&efYd=20250621",
            "법령명한글": "공중보건장학을 위한 특례법",
            "법령구분명": "법률",
            "소관부처명": "보건복지부",
            "공포번호": "20445",
            "제개정구분명": "타법개정",
            "소관부처코드": "1352000",
            "id": "876",
            "법령ID": "000216",
            "공동부령정보": "",
            "시행일자": "20250621",
            "공포일자": "20240920",
            "법령약칭명": "공중보건장학법"
        },
        {
            "현행연혁코드": "연혁",
            "법령일련번호": "271427",
            "자법타법여부": "",
            "법령상세링크": "/DRF/lawService.do?OC=knowhow1&target=eflaw&MST=271427&type=HTML&mobileYn=&efYd=20250621",
            "법령명한글": "고등교육법 시행령",
            "법령구분명": "대통령령",
            "소관부처명": "교육부",
            "공포번호": "35554",
            "제개정구분명": "일부개정",
            "소관부처코드": "1342000",
            "id": "877",
            "법령ID": "002233",
            "공동부령정보": "",
            "시행일자": "20250621",
            "공포일자": "20250602",
            "법령약칭명": ""
        },
        {
            "현행연혁코드": "현행",
            "법령일련번호": "271431",
            "자법타법여부": "",
            "법령상세링크": "/DRF/lawService.do?OC=knowhow1&target=eflaw&MST=271431&type=HTML&mobileYn=&efYd=20250621",
            "법령명한글": "고등교육법 시행령",
            "법령구분명": "대통령령",
            "소관부처명": "교육부",
            "공포번호": "35555",
            "제개정구분명": "타법개정",
            "소관부처코드": "1342000",
            "id": "878",
            "법령ID": "002233",
            "공동부령정보": "",
            "시행일자": "20250621",
            "공포일자": "20250602",
            "법령약칭명": ""
        },
        {
            "현행연혁코드": "연혁",
            "법령일련번호": "267347",
            "자법타법여부": "",
            "법령상세링크": "/DRF/lawService.do?OC=knowhow1&target=eflaw&MST=267347&type=HTML&mobileYn=&efYd=20250621",
            "법령명한글": "고등교육법",
            "법령구분명": "법률",
            "소관부처명": "교육부",
            "공포번호": "20561",
            "제개정구분명": "일부개정",
            "소관부처코드": "1342000",
            "id": "879",
            "법령ID": "000899",
            "공동부령정보": "",
            "시행일자": "20250621",
            "공포일자": "20241220",
            "법령약칭명": ""
        },
        {
            "현행연혁코드": "연혁",
            "법령일련번호": "271469",
            "자법타법여부": "",
            "법령상세링크": "/DRF/lawService.do?OC=knowhow1&target=eflaw&MST=271469&type=HTML&mobileYn=&efYd=20250621",
            "법령명한글": "감염병의 예방 및 관리에 관한 법률 시행령",
            "법령구분명": "대통령령",
            "소관부처명": "보건복지부,질병관리청",
            "공포번호": "35574",
            "제개정구분명": "일부개정",
            "소관부처코드": "1352000,1790387",
            "id": "880",
            "법령ID": "004750",
            "공동부령정보": "",
            "시행일자": "20250621",
            "공포일자": "20250602",
            "법령약칭명": "감염병예방법 시행령"
        },
        {
            "현행연혁코드": "연혁",
            "법령일련번호": "271529",
            "자법타법여부": "",
            "법령상세링크": "/DRF/lawService.do?OC=knowhow1&target=eflaw&MST=271529&type=HTML&mobileYn=&efYd=20250621",
            "법령명한글": "감염병의 예방 및 관리에 관한 법률 시행규칙",
            "법령구분명": "보건복지부령",
            "소관부처명": "보건복지부,질병관리청",
            "공포번호": "01114",
            "제개정구분명": "일부개정",
            "소관부처코드": "1352000,1790387",
            "id": "881",
            "법령ID": "008083",
            "공동부령정보": "",
            "시행일자": "20250621",
            "공포일자": "20250602",
            "법령약칭명": "감염병예방법 시행규칙"
        },
        {
            "현행연혁코드": "연혁",
            "법령일련번호": "267371",
            "자법타법여부": "",
            "법령상세링크": "/DRF/lawService.do?OC=knowhow1&target=eflaw&MST=267371&type=HTML&mobileYn=&efYd=20250621",
            "법령명한글": "감염병의 예방 및 관리에 관한 법률",
            "법령구분명": "법률",
            "소관부처명": "보건복지부,질병관리청",
            "공포번호": "20583",
            "제개정구분명": "일부개정",
            "소관부처코드": "1352000,1790387",
            "id": "882",
            "법령ID": "001792",
            "공동부령정보": "",
            "시행일자": "20250621",
            "공포일자": "20241220",
            "법령약칭명": "감염병예방법"
        },
        {
            "현행연혁코드": "연혁",
            "법령일련번호": "265455",
            "자법타법여부": "",
            "법령상세링크": "/DRF/lawService.do?OC=knowhow1&target=eflaw&MST=265455&type=HTML&mobileYn=&efYd=20250621",
            "법령명한글": "감염병의 예방 및 관리에 관한 법률",
            "법령구분명": "법률",
            "소관부처명": "보건복지부,질병관리청",
            "공포번호": "20445",
            "제개정구분명": "타법개정",
            "소관부처코드": "1352000,1790387",
            "id": "883",
            "법령ID": "001792",
            "공동부령정보": "",
            "시행일자": "20250621",
            "공포일자": "20240920",
            "법령약칭명": "감염병예방법"
        },
        {
            "현행연혁코드": "현행",
            "법령일련번호": "272437",
            "자법타법여부": "",
            "법령상세링크": "/DRF/lawService.do?OC=knowhow1&target=eflaw&MST=272437&type=HTML&mobileYn=&efYd=20250621",
            "법령명한글": "간호법 시행령",
            "법령구분명": "대통령령",
            "소관부처명": "보건복지부",
            "공포번호": "35597",
            "제개정구분명": "제정",
            "소관부처코드": "1352000",
            "id": "884",
            "법령ID": "014898",
            "공동부령정보": "",
            "시행일자": "20250621",
            "공포일자": "20250620",
            "법령약칭명": ""
        },
        {
            "현행연혁코드": "현행",
            "법령일련번호": "272543",
            "자법타법여부": "",
            "법령상세링크": "/DRF/lawService.do?OC=knowhow1&target=eflaw&MST=272543&type=HTML&mobileYn=&efYd=20250621",
            "법령명한글": "간호법 시행규칙",
            "법령구분명": "보건복지부령",
            "소관부처명": "보건복지부",
            "공포번호": "01118",
            "제개정구분명": "제정",
            "소관부처코드": "1352000",
            "id": "885",
            "법령ID": "014900",
            "공동부령정보": "",
            "시행일자": "20250621",
            "공포일자": "20250620",
            "법령약칭명": ""
        },
        {
            "현행연혁코드": "현행",
            "법령일련번호": "265413",
            "자법타법여부": "",
            "법령상세링크": "/DRF/lawService.do?OC=knowhow1&target=eflaw&MST=265413&type=HTML&mobileYn=&efYd=20250621",
            "법령명한글": "간호법",
            "법령구분명": "법률",
            "소관부처명": "보건복지부",
            "공포번호": "20445",
            "제개정구분명": "제정",
            "소관부처코드": "1352000",
            "id": "886",
            "법령ID": "014736",
            "공동부령정보": "",
            "시행일자": "20250621",
            "공포일자": "20240920",
            "법령약칭명": ""
        },
        {
            "현행연혁코드": "현행",
            "법령일련번호": "272439",
            "자법타법여부": "",
            "법령상세링크": "/DRF/lawService.do?OC=knowhow1&target=eflaw&MST=272439&type=HTML&mobileYn=&efYd=20250621",
            "법령명한글": "가습기살균제 피해구제를 위한 특별법 시행령",
            "법령구분명": "대통령령",
            "소관부처명": "환경부",
            "공포번호": "35597",
            "제개정구분명": "타법개정",
            "소관부처코드": "1480000",
            "id": "887",
            "법령ID": "012969",
            "공동부령정보": "",
            "시행일자": "20250621",
            "공포일자": "20250620",
            "법령약칭명": ""
        },
        {
            "현행연혁코드": "현행",
            "법령일련번호": "272435",
            "자법타법여부": "",
            "법령상세링크": "/DRF/lawService.do?OC=knowhow1&target=eflaw&MST=272435&type=HTML&mobileYn=&efYd=20250620",
            "법령명한글": "주민투표관리규칙",
            "법령구분명": "중앙선거관리위원회규칙",
            "소관부처명": "중앙선거관리위원회",
            "공포번호": "00629",
            "제개정구분명": "일부개정",
            "소관부처코드": "9760000",
            "id": "888",
            "법령ID": "009729",
            "공동부령정보": "",
            "시행일자": "20250620",
            "공포일자": "20250620",
            "법령약칭명": ""
        },
        {
            "현행연혁코드": "현행",
            "법령일련번호": "272433",
            "자법타법여부": "",
            "법령상세링크": "/DRF/lawService.do?OC=knowhow1&target=eflaw&MST=272433&type=HTML&mobileYn=&efYd=20250620",
            "법령명한글": "인구주택총조사 규칙",
            "법령구분명": "기획재정부령",
            "소관부처명": "통계청",
            "공포번호": "01130",
            "제개정구분명": "일부개정",
            "소관부처코드": "1240000",
            "id": "889",
            "법령ID": "007885",
            "공동부령정보": "",
            "시행일자": "20250620",
            "공포일자": "20250620",
            "법령약칭명": ""
        },
        {
            "현행연혁코드": "연혁",
            "법령일련번호": "272469",
            "자법타법여부": "",
            "법령상세링크": "/DRF/lawService.do?OC=knowhow1&target=eflaw&MST=272469&type=HTML&mobileYn=&efYd=20250620",
            "법령명한글": "선거관리위원회 공무원 규칙",
            "법령구분명": "중앙선거관리위원회규칙",
            "소관부처명": "중앙선거관리위원회",
            "공포번호": "00630",
            "제개정구분명": "일부개정",
            "소관부처코드": "9760000",
            "id": "890",
            "법령ID": "006042",
            "공동부령정보": "",
            "시행일자": "20250620",
            "공포일자": "20250620",
            "법령약칭명": ""
        },
        {
            "현행연혁코드": "현행",
            "법령일련번호": "269807",
            "자법타법여부": "",
            "법령상세링크": "/DRF/lawService.do?OC=knowhow1&target=eflaw&MST=269807&type=HTML&mobileYn=&efYd=20250619",
            "법령명한글": "취업 후 학자금 상환 특별법",
            "법령구분명": "법률",
            "소관부처명": "교육부",
            "공포번호": "20788",
            "제개정구분명": "일부개정",
            "소관부처코드": "1342000",
            "id": "891",
            "법령ID": "011136",
            "공동부령정보": "",
            "시행일자": "20250619",
            "공포일자": "20250318",
            "법령약칭명": "학자금상환법"
        },
        {
            "현행연혁코드": "현행",
            "법령일련번호": "272421",
            "자법타법여부": "",
            "법령상세링크": "/DRF/lawService.do?OC=knowhow1&target=eflaw&MST=272421&type=HTML&mobileYn=&efYd=20250619",
            "법령명한글": "식품ㆍ의약품분야 시험ㆍ검사 등에 관한 법률 시행규칙",
            "법령구분명": "총리령",
            "소관부처명": "식품의약품안전처",
            "공포번호": "02037",
            "제개정구분명": "일부개정",
            "소관부처코드": "1471000",
            "id": "892",
            "법령ID": "012135",
            "공동부령정보": "",
            "시행일자": "20250619",
            "공포일자": "20250619",
            "법령약칭명": "식품의약품검사법 시행규칙"
        },
        {
            "현행연혁코드": "연혁",
            "법령일련번호": "269919",
            "자법타법여부": "",
            "법령상세링크": "/DRF/lawService.do?OC=knowhow1&target=eflaw&MST=269919&type=HTML&mobileYn=&efYd=20250619",
            "법령명한글": "병역법",
            "법령구분명": "법률",
            "소관부처명": "국방부,병무청",
            "공포번호": "20808",
            "제개정구분명": "일부개정",
            "소관부처코드": "1290000,1300000",
            "id": "893",
            "법령ID": "001622",
            "공동부령정보": "",
            "시행일자": "20250619",
            "공포일자": "20250318",
            "법령약칭명": ""
        },
        {
            "현행연혁코드": "연혁",
            "법령일련번호": "269953",
            "자법타법여부": "",
            "법령상세링크": "/DRF/lawService.do?OC=knowhow1&target=eflaw&MST=269953&type=HTML&mobileYn=&efYd=20250619",
            "법령명한글": "방위사업법",
            "법령구분명": "법률",
            "소관부처명": "국방부,방위사업청,산업통상자원부",
            "공포번호": "20807",
            "제개정구분명": "일부개정",
            "소관부처코드": "1290000,1450000,1690000",
            "id": "894",
            "법령ID": "010107",
            "공동부령정보": "",
            "시행일자": "20250619",
            "공포일자": "20250318",
            "법령약칭명": ""
        },
        {
            "현행연혁코드": "연혁",
            "법령일련번호": "269961",
            "자법타법여부": "",
            "법령상세링크": "/DRF/lawService.do?OC=knowhow1&target=eflaw&MST=269961&type=HTML&mobileYn=&efYd=20250619",
            "법령명한글": "마약류 관리에 관한 법률",
            "법령구분명": "법률",
            "소관부처명": "보건복지부,식품의약품안전처",
            "공포번호": "20814",
            "제개정구분명": "일부개정",
            "소관부처코드": "1352000,1471000",
            "id": "895",
            "법령ID": "002025",
            "공동부령정보": "",
            "시행일자": "20250619",
            "공포일자": "20250318",
            "법령약칭명": "마약류관리법"
        },
        {
            "현행연혁코드": "현행",
            "법령일련번호": "272463",
            "자법타법여부": "",
            "법령상세링크": "/DRF/lawService.do?OC=knowhow1&target=eflaw&MST=272463&type=HTML&mobileYn=&efYd=20250618",
            "법령명한글": "환경기술 및 환경산업 지원법 시행규칙",
            "법령구분명": "환경부령",
            "소관부처명": "환경부",
            "공포번호": "01181",
            "제개정구분명": "일부개정",
            "소관부처코드": "1480000",
            "id": "896",
            "법령ID": "008748",
            "공동부령정보": "",
            "시행일자": "20250618",
            "공포일자": "20250618",
            "법령약칭명": "환경기술산업법 시행규칙"
        },
        {
            "현행연혁코드": "현행",
            "법령일련번호": "272461",
            "자법타법여부": "",
            "법령상세링크": "/DRF/lawService.do?OC=knowhow1&target=eflaw&MST=272461&type=HTML&mobileYn=&efYd=20250618",
            "법령명한글": "지진ㆍ지진해일ㆍ화산의 관측 및 경보에 관한 법률 시행규칙",
            "법령구분명": "환경부령",
            "소관부처명": "기상청",
            "공포번호": "01180",
            "제개정구분명": "일부개정",
            "소관부처코드": "1360000",
            "id": "897",
            "법령ID": "012244",
            "공동부령정보": "",
            "시행일자": "20250618",
            "공포일자": "20250618",
            "법령약칭명": "지진관측법 시행규칙"
        },
        {
            "현행연혁코드": "현행",
            "법령일련번호": "272467",
            "자법타법여부": "",
            "법령상세링크": "/DRF/lawService.do?OC=knowhow1&target=eflaw&MST=272467&type=HTML&mobileYn=&efYd=20250618",
            "법령명한글": "위생용품 관리법 시행규칙",
            "법령구분명": "총리령",
            "소관부처명": "식품의약품안전처",
            "공포번호": "02036",
            "제개정구분명": "일부개정",
            "소관부처코드": "1471000",
            "id": "898",
            "법령ID": "013110",
            "공동부령정보": "",
            "시행일자": "20250618",
            "공포일자": "20250618",
            "법령약칭명": ""
        },
        {
            "현행연혁코드": "현행",
            "법령일련번호": "267127",
            "자법타법여부": "",
            "법령상세링크": "/DRF/lawService.do?OC=knowhow1&target=eflaw&MST=267127&type=HTML&mobileYn=&efYd=20250618",
            "법령명한글": "어린이놀이시설 안전관리법 시행령",
            "법령구분명": "대통령령",
            "소관부처명": "행정안전부",
            "공포번호": "35079",
            "제개정구분명": "일부개정",
            "소관부처코드": "1741000",
            "id": "899",
            "법령ID": "010575",
            "공동부령정보": "",
            "시행일자": "20250618",
            "공포일자": "20241217",
            "법령약칭명": "어린이놀이시설법 시행령"
        },
        {
            "현행연혁코드": "연혁",
            "법령일련번호": "272465",
            "자법타법여부": "",
            "법령상세링크": "/DRF/lawService.do?OC=knowhow1&target=eflaw&MST=272465&type=HTML&mobileYn=&efYd=20250618",
            "법령명한글": "문화체육관광부와 그 소속기관 직제 시행규칙",
            "법령구분명": "문화체육관광부령",
            "소관부처명": "문화체육관광부",
            "공포번호": "00605",
            "제개정구분명": "일부개정",
            "소관부처코드": "1371000",
            "id": "900",
            "법령ID": "010697",
            "공동부령정보": "",
            "시행일자": "20250618",
            "공포일자": "20250618",
            "법령약칭명": ""
        }
    ],
    "resultMsg": "success",
    "키워드": "*",
    "page": "9",
    "resultCode": "00",
    "target": "eflaw",
    "totalCnt": "2882",
    "section": "lawNm",
    "numOfRows": "100"
}}